LICENSE
MANIFEST.in
README.md
requirements.txt
setup.py
crmodel/config.py
crmodel/crmodel.py
crmodel/model.py
crmodel/segmentationReader.py
crmodel/utils.py
crmodel.egg-info/PKG-INFO
crmodel.egg-info/SOURCES.txt
crmodel.egg-info/dependency_links.txt
crmodel.egg-info/requires.txt
crmodel.egg-info/top_level.txt