Metadata-Version: 2.1
Name: crmodel
Version: 0.4.5
Summary: crmodel is a python package that produces the crossroadsdesriber model from OpenStreetMap. See doi.org/10.5194/agile-giss-3-40-2022 for further informations.
Home-page: https://github.com/jeremyk6/crmodel
Author: Jérémy Kalsron
Author-email: jeremy.kalsron@gmail.com  
License: AGPL-3.0
Classifier: License :: OSI Approved :: GNU Affero General Public License v3 or later (AGPLv3+)
Classifier: Programming Language :: Python :: 3
Classifier: Programming Language :: Python :: 3.7
License-File: LICENSE
